<?xml version="1.0" encoding="UTF-8"?>
<objects serializationModel="Studio.02.02.00">
	<object class="AudioFile" id="{6c15be66-7618-4287-a9ac-8d27397b7670}">
		<property name="assetPath">
			<value>lucia_attack3.mp3</value>
		</property>
		<property name="frequencyInKHz">
			<value>48</value>
		</property>
		<property name="channelCount">
			<value>2</value>
		</property>
		<property name="length">
			<value>0.16800000000000001</value>
		</property>
		<relationship name="masterAssetFolder">
			<destination>{837ee598-8eee-4e58-9b47-225c973e16db}</destination>
		</relationship>
	</object>
</objects>
